{
	"name": "UsersTbl",
	"properties": {
		"linkedServiceName": {
			"referenceName": "OutputSQL",
			"type": "LinkedServiceReference"
		},
		"folder": {
			"name": "SQL_tbl"
		},
		"annotations": [],
		"type": "AzureSqlTable",
		"schema": [
			{
				"name": "user_id",
				"type": "int",
				"precision": 10
			},
			{
				"name": "username",
				"type": "varchar"
			},
			{
				"name": "email",
				"type": "varchar"
			},
			{
				"name": "total_points_earned",
				"type": "int",
				"precision": 10
			},
			{
				"name": "current_balance",
				"type": "int",
				"precision": 10
			},
			{
				"name": "level",
				"type": "int",
				"precision": 10
			},
			{
				"name": "xp",
				"type": "int",
				"precision": 10
			},
			{
				"name": "created_at",
				"type": "date"
			}
		],
		"typeProperties": {
			"schema": "dbo",
			"table": "users"
		}
	},
	"type": "Microsoft.DataFactory/factories/datasets"
}